db_name_to_idx_mapper/__init__.py
db_name_to_idx_mapper/cli.py
db_name_to_idx_mapper/config_path.py
db_name_to_idx_mapper/db_name_to_idx_mapper.py
db_name_to_idx_mapper-1.0.3a0.dist-info/METADATA
db_name_to_idx_mapper-1.0.3a0.dist-info/WHEEL
db_name_to_idx_mapper-1.0.3a0.dist-info/entry_points.txt
db_name_to_idx_mapper-1.0.3a0.dist-info/licenses/LICENSE
db_name_to_idx_mapper-1.0.3a0.dist-info/RECORD
