Metadata-Version: 2.4
Name: db-name-to-idx-mapper
Version: 1.0.3a0
Summary: Cross-platform utility for mapping database names to sequential indices
Project-URL: Homepage, https://github.com/velis74/db-name-to-idx-mapper
Project-URL: Repository, https://github.com/velis74/db-name-to-idx-mapper
Project-URL: Bug Tracker, https://github.com/velis74/db-name-to-idx-mapper/issues
Author-email: "Velis d.o.o." <support@velis.si>
License: MIT
License-File: LICENSE
Classifier: Development Status :: 4 - Beta
Classifier: License :: OSI Approved :: MIT License
Classifier: Operating System :: OS Independent
Classifier: Programming Language :: Python :: 3
Classifier: Topic :: Database
Classifier: Topic :: System :: Systems Administration
Classifier: Topic :: Utilities
Requires-Python: >=3.7
